{"lastUsed":1585900531033,"path":"C:\/DATA\/JAVA\/0403","projectCount":2,"recentFiles":[{"path":"\/ex01\/src\/ex01","parentWorkspace":"C:\/DATA\/JAVA\/0403","name":"StudentDAO.java","lastModified":1585898155238,"locationURI":"file:\/C:\/DATA\/JAVA\/0403\/ex01\/src\/ex01\/StudentDAO.java"},{"path":"\/ex02\/WebContent","parentWorkspace":"C:\/DATA\/JAVA\/0403","name":"ex01.html","lastModified":1585899520088,"locationURI":"file:\/C:\/DATA\/JAVA\/0403\/ex02\/WebContent\/ex01.html"},{"path":"\/ex01\/src\/ex01","parentWorkspace":"C:\/DATA\/JAVA\/0403","name":"Sample.java","lastModified":1585900532906,"locationURI":"file:\/C:\/DATA\/JAVA\/0403\/ex01\/src\/ex01\/Sample.java"},{"path":"\/ex01\/src\/ex01","parentWorkspace":"C:\/DATA\/JAVA\/0403","name":"StudentVO.java","lastModified":1585879340317,"locationURI":"file:\/C:\/DATA\/JAVA\/0403\/ex01\/src\/ex01\/StudentVO.java"}]}